tridesclous/__init__.py
tridesclous/autoparams.py
tridesclous/catalogueconstructor.py
tridesclous/cataloguetools.py
tridesclous/cleancluster.py
tridesclous/cltools.py
tridesclous/cluster.py
tridesclous/dataio.py
tridesclous/datasets.py
tridesclous/datasource.py
tridesclous/decomposition.py
tridesclous/dip.py
tridesclous/export.py
tridesclous/importers.py
tridesclous/iotools.py
tridesclous/jobtools.py
tridesclous/labelcodes.py
tridesclous/matplotlibplot.py
tridesclous/metrics.py
tridesclous/numba_tools.py
tridesclous/peakdetector.py
tridesclous/peeler.py
tridesclous/peeler_cl.py
tridesclous/peeler_engine_base.py
tridesclous/peeler_engine_geometry.py
tridesclous/peeler_engine_geometry_cl.py
tridesclous/peeler_engine_testing.py
tridesclous/peeler_tools.py
tridesclous/probe_list.py
tridesclous/pruningshears.py
tridesclous/pythran_tools.py
tridesclous/report.py
tridesclous/sawchaincut.py
tridesclous/signalpreprocessor.py
tridesclous/tools.py
tridesclous/version.py
tridesclous/waveformtools.py
tridesclous/gui/__init__.py
tridesclous/gui/base.py
tridesclous/gui/baselist.py
tridesclous/gui/cataloguecontroller.py
tridesclous/gui/cataloguewindow.py
tridesclous/gui/crosscorrelogramviewer.py
tridesclous/gui/featuretimeviewer.py
tridesclous/gui/gpuselector.py
tridesclous/gui/gui_params.py
tridesclous/gui/initializedatasetwindow.py
tridesclous/gui/isiviewer.py
tridesclous/gui/mainwindow.py
tridesclous/gui/myqt.py
tridesclous/gui/ndscatter.py
tridesclous/gui/pairlist.py
tridesclous/gui/peaklists.py
tridesclous/gui/peelercontroller.py
tridesclous/gui/peelerwindow.py
tridesclous/gui/probegeometryview.py
tridesclous/gui/silhouette.py
tridesclous/gui/similarity.py
tridesclous/gui/spikelists.py
tridesclous/gui/test_gpuselector.py
tridesclous/gui/tools.py
tridesclous/gui/traceviewer.py
tridesclous/gui/waveformhistviewer.py
tridesclous/gui/waveformviewer.py
tridesclous/gui/icons/__init__.py
tridesclous/gui/icons/icons_py3.py
tridesclous/gui/icons/make_ressources.py
tridesclous-1.6.9.dist-info/METADATA
tridesclous-1.6.9.dist-info/WHEEL
tridesclous-1.6.9.dist-info/entry_points.txt
tridesclous-1.6.9.dist-info/top_level.txt
tridesclous-1.6.9.dist-info/RECORD
